{
	"name": "StormBreaker",
	"description": "It is fast, like a light; It is deadly, like a death; it is beautiful like a diamond; It is StormBreaker!",
	"type": "Omega",
	"drillPower": 2,
	"mineSpeed": 1,
	"buildPower": 10,
	"itemCapacity": 35,
	"flying": true,
	"maxVelocity": 2.5,
	"speed": 1,
	"mass": 1,
	"drag": 0.07,
	"engineColor": "84f491",
	"engineOffset": 4,
	"engineSize": 2,
	"health": 1200,
	"rotateWeapon": false,
	"weapon": {
		"reload": 10,
		"shots": 1,
		"ejectEffect": "none",
		"shake": 0.0,
		"ignoreRotation": false,
		"bullet": {
			"speed": 10,
			"damage": 50,
			"lifeTime": 30,
			"splashDamage": 100,
			"splashDamageRadius": 16
		},
		"shootSound": "pew"
	}
}